{
  "canonicalUrl": "https://dontstarve.wiki.gg/wiki/Walrus_Tusk",
  "categories": [
    "Items",
    "Non-Flammable",
    "Pages_with_navboxes",
    "Resources",
    "Winter"
  ],
  "displayTitle": "<span class=\"mw-page-title-main\">Walrus Tusk</span>",
  "html": "<div class=\"mw-content-ltr mw-parser-output\">\n<p class=\"mw-empty-elt\"></p>\n\n<p class=\"mw-empty-elt\"></p>\n\n<p>The <b>Walrus Tusk</b> is an <a href=\"https://dontstarve.wiki.gg/wiki/Item\" class=\"mw-redirect\" title=\"Item\">Item</a> sometimes dropped by <a href=\"https://dontstarve.wiki.gg/wiki/MacTusk\" title=\"MacTusk\">MacTusk</a>. Walrus Tusks can be used to craft the <a href=\"https://dontstarve.wiki.gg/wiki/Walking_Cane\" title=\"Walking Cane\">Walking Cane</a> and <a href=\"https://dontstarve.wiki.gg/wiki/Brush\" title=\"Brush\">Brush</a> at an <a href=\"https://dontstarve.wiki.gg/wiki/Alchemy_Engine\" title=\"Alchemy Engine\">Alchemy Engine</a>.\n</p>\n<h2><span class=\"mw-headline\" id=\"Downloadable_Content\"><a href=\"https://dontstarve.wiki.gg/wiki/Gift_Icon\" title=\"Gift Icon\"><img alt=\"Gift Icon.png\" src=\"https://dontstarve.wiki.gg/images/thumb/Gift_Icon.png/32px-Gift_Icon.png?8b4efa\" width=\"32\" height=\"32\"></a> Downloadable Content</span></h2>\n<p>Walrus Tusks are also included in the <i><a href=\"https://dontstarve.wiki.gg/wiki/Don%27t_Starve:_Hamlet\" title=\"Don&#x27;t Starve: Hamlet\">Hamlet</a></i> DLC. However, they can only be bought for 50 <a href=\"https://dontstarve.wiki.gg/wiki/Oinc\" title=\"Oinc\">Oincs</a> each at <a href=\"https://dontstarve.wiki.gg/wiki/%27The_Sty%27_Oddities_Emporium\" title=\"&#x27;The Sty&#x27; Oddities Emporium\">&#x27;The Sty&#x27; Oddities Emporium</a> in the <a href=\"https://dontstarve.wiki.gg/wiki/Pig_City\" title=\"Pig City\">Pig City</a>.\n</p>\n<h2><span class=\"mw-headline\" id=\"Trivia\"><a href=\"https://dontstarve.wiki.gg/wiki/Placeholder\" title=\"Placeholder\"><img alt=\"Placeholder.png\" src=\"https://dontstarve.wiki.gg/images/thumb/Placeholder.png/32px-Placeholder.png?210282\" width=\"32\" height=\"32\"></a> Trivia</span></h2>\n<ul><li>Before the <i><a href=\"https://dontstarve.wiki.gg/wiki/Don%27t_Starve/Version_History#April_9,_2013_-_The_End_is_Nigh\" title=\"Don&#x27;t Starve/Version History\">The End is Nigh</a></i> update, the Walrus Tusk had no use.</li></ul>\n\n\n\n\n\n</div>",
  "images": [
    {
      "height": 64,
      "mime": "image/png",
      "src": "/assets/wiki/7009db5141e5cc102685734bcac1fe28630d78da349eb18a1fdfee83d414fea8.png",
      "title": "File:Walrus Tusk.png",
      "width": 64
    }
  ],
  "normalized": {
    "dropTable": {
      "rows": [
        {
          "chance": "50%",
          "context": null,
          "quantity": "1",
          "sources": [
            {
              "entityId": null,
              "iconUrl": "https://dontstarve.wiki.gg/wiki/Special:Redirect/file/MacTusk.png",
              "title": "MacTusk",
              "url": "https://dontstarve.wiki.gg/wiki/MacTusk"
            }
          ]
        }
      ]
    },
    "schema_version": 2,
    "subject": {
      "entityId": "base_game:walrus_tusk",
      "iconUrl": null,
      "title": "Walrus Tusk",
      "url": "https://dontstarve.wiki.gg/wiki/Walrus_Tusk"
    },
    "usage": {
      "recipes": [
        {
          "character": null,
          "dlc": null,
          "ingredients": [
            {
              "amount": 2,
              "item": {
                "entityId": "base_game:goldnugget",
                "iconUrl": null,
                "title": "Gold Nugget",
                "url": "https://dontstarve.wiki.gg/wiki/Gold_Nugget"
              }
            },
            {
              "amount": 4,
              "item": {
                "entityId": "base_game:twigs",
                "iconUrl": null,
                "title": "Twigs",
                "url": "https://dontstarve.wiki.gg/wiki/Twigs"
              }
            }
          ],
          "note": null,
          "result": {
            "entityId": "base_game:cane",
            "iconUrl": null,
            "title": "Walking Cane",
            "url": "https://dontstarve.wiki.gg/wiki/Walking_Cane"
          },
          "resultAmount": 1,
          "station": "Alchemy Engine",
          "subjectAmount": 1
        },
        {
          "character": null,
          "dlc": null,
          "ingredients": [
            {
              "amount": 1,
              "item": {
                "entityId": "base_game:steelwool",
                "iconUrl": null,
                "title": "Steel Wool",
                "url": "https://dontstarve.wiki.gg/wiki/Steel_Wool"
              }
            },
            {
              "amount": 2,
              "item": {
                "entityId": "base_game:goldnugget",
                "iconUrl": null,
                "title": "Gold Nugget",
                "url": "https://dontstarve.wiki.gg/wiki/Gold_Nugget"
              }
            }
          ],
          "note": null,
          "result": {
            "entityId": "base_game:brush",
            "iconUrl": null,
            "title": "Brush",
            "url": "https://dontstarve.wiki.gg/wiki/Brush"
          },
          "resultAmount": 1,
          "station": "Alchemy Engine",
          "subjectAmount": 1
        }
      ]
    }
  },
  "pageId": 198162,
  "plainText": "Don't Starve\nTogether\nWalrus Tusk\nObject Info\n10\nSource\n: ( ×50)\nDropped by\n50%\nMiscellaneous\n\"walrus_tusk\"\n“I'm sure I'll find a use for it eventually.”\n–Wilson\n“Nom nom nom.”\n–Willow\n“Sea cow man tooth!”\n–Wolfgang\n“I gnash thee.”\n–Wendy\n“IT WASN'T MUCH HELP TO ITS ORIGINAL OWNER”\n–WX-78\n“This would be useful for scrimshaw.”\n–Wickerbottom\n“He had a cavity, eh?”\n–Woodie\n“I'll put this to better use.”\n–Maxwell\n“Just as I suspected. It's a big tooth.”\n–Wagstaff\n“Rended fröm the möuth öf the sea beast.”\n–Wigfrid\n“Maybe we can use it for arts and crafts.”\n–Webber\n“That's a pretty impressive tooth.”\n–Walani\n“It won't be needing this anymore.”\n–Warly\n“Ye'd make a fancy new peg leg.”\n–Woodlegs\n“YOUR OWN SELF BE TOOTH”\n–Wilba\n“Tooth branch”\n–Wormwood\n“Big deal, it's a tooth. I have a bunch of them in my mouth.”\n–Wheeler\n“Get a load of this chomper!”\n–Winona\n“A sideways horn for a wizened face.”\n–Wortox\n“Took his tooth!”\n–Wurt\n“Oof... I don't think he brushed.”\n–Walter\n“I should pocket it for future tinkering.”\n–Wanda\nThe Walrus Tusk is an Item sometimes dropped by MacTusk. Walrus Tusks can be used to craft the Walking Cane and Brush at an Alchemy Engine.\nDownloadable Content[edit | edit source]\nWalrus Tusks are also included in the Hamlet DLC. However, they can only be bought for 50 Oincs each at 'The Sty' Oddities Emporium in the Pig City.\nUsage[edit | edit source]\n×2\n×4\n×2\nTrivia[edit | edit source]\nBefore the The End is Nigh update, the Walrus Tusk had no use.\nView or edit this template\nResources\nAttention: The following categories are only for the players look up the page based on their first impression, they have nothing to do with the actual categories/behavior/function/tags of these items\nPlants\nNatural non-living materials\nMobs Parts\nSkins\nFeathers\nBones and horns\nGems\nShadow Resources\nLunar Resources\nCraftable Resources\nNon-natural materials\nTrinkets\nLost Relics\nTransmission Items",
  "recipes": [],
  "redirectTarget": null,
  "revision": {
    "id": 558631,
    "sha1": "799f95e6ab863bc1c7524ef05c8efb17aa70e567",
    "timestamp": "2026-04-15T03:15:56Z"
  },
  "schema_version": 1,
  "summaryViHtml": "<h2>Tóm tắt</h2><p>Ngà hải mã là một Vật phẩm đôi khi bị MacTusk đánh rơi. Ngà Hải Mã có thể được sử dụng để chế tạo Gậy Đi Bộ và Bàn Chải tại Máy Luyện Kim.</p>",
  "title": "Walrus Tusk",
  "wikitext": "{{Navbutton/Separation}}\n{{Object Infobox\n|icon = Walrus Tusk.png\n|image = Walrus Tusk Dropped.png\n|droppedBy = {{pic|30|MacTusk}} 50%\n|soldBy ={{Pic|24|Hamlet icon}}: {{Pic|32|'The Sty' Oddities Emporium}} ({{Pic|24|Oinc}} &times;50)\n|stack = 10\n|spawnCode = \"walrus_tusk\"|renewable?=yes}}\n{{Quotes\n|wilson = I'm sure I'll find a use for it eventually.\n|willow = Nom nom nom.\n|wolfgang = Sea cow man tooth!\n|wendy = I gnash thee.\n|wx78 = IT WASN'T MUCH HELP TO ITS ORIGINAL OWNER\n|wickerbottom = This would be useful for scrimshaw.\n|woodie = He had a cavity, eh?\n|maxwell = I'll put this to better use.\n|wagstaff = Just as I suspected. It's a big tooth.\n|wigfrid = Rended fröm the möuth öf the sea beast.\n|webber = Maybe we can use it for arts and crafts.\n|walani = That's a pretty impressive tooth.\n|warly = It won't be needing this anymore.\n|woodlegs = Ye'd make a fancy new peg leg.\n|wilba = YOUR OWN SELF BE TOOTH\n|wormwood = Tooth branch\n|wheeler =Big deal, it's a tooth. I have a bunch of them in my mouth. \n|winona = Get a load of this chomper!\n|wortox = A sideways horn for a wizened face.\n|wurt = Took his tooth!\n|walter = Oof... I don't think he brushed.\n|wanda = I should pocket it for future tinkering. \n|choose = wolfgang}}\n\nThe '''Walrus Tusk''' is an [[Item]] sometimes dropped by [[MacTusk]]. Walrus Tusks can be used to craft the [[Walking Cane]] and [[Brush]] at an [[Alchemy Engine]].\n=={{Pic32|Gift Icon}} Downloadable Content ==\nWalrus Tusks are also included in the ''[[Don't Starve: Hamlet|Hamlet]]'' DLC. However, they can only be bought for 50 [[Oinc]]s each at [['The Sty' Oddities Emporium]] in the [[Pig City]].\n\n=={{pic|32|Icon Tools}} Usage==\n{{Recipe\n|item1 = Walrus Tusk\n|item2 = Gold Nugget\n|count2 = 2\n|item3 = Twigs\n|count3 = 4\n|tool = Alchemy Engine\n|result = Walking Cane}}\n\n{{Recipe\n|item1 = Walrus Tusk\n|item2 = Steel Wool\n|item3 = Gold Nugget\n|count3 = 2\n|tool = Alchemy Engine\n|result = Brush}}\n=={{pic|32|Placeholder}} Trivia==\n* Before the ''[[Don't Starve/Version History#April 9, 2013 - The End is Nigh|The End is Nigh]]'' update, the Walrus Tusk had no use.\n\n{{Mob Dropped Items}}\n[[vi:Ngà Hải Mã]]\n[[Category:Winter]]\n[[Category:Items]]\n[[Category:Resources]]\n[[Category:Non-Flammable]]"
}
