{
  "canonicalUrl": "https://dontstarve.wiki.gg/wiki/Mant_Suit",
  "categories": [
    "Armor",
    "Craftable_Items",
    "Craftable_Items_and_Structures_on_DST",
    "DST-Specific_Pages",
    "Equipable_Items",
    "Fight_Tab",
    "Hamlet",
    "Items",
    "Pages_using_Tabber_parser_tag",
    "Pages_with_navboxes",
    "Science_Tier_1"
  ],
  "displayTitle": "<span class=\"mw-page-title-main\">Mant Suit</span>",
  "html": "<div class=\"mw-content-ltr mw-parser-output\"><p><i>Exclusive to:</i> <a href=\"https://dontstarve.wiki.gg/wiki/Hamlet\" title=\"Hamlet\"><img alt=\"Hamlet icon.png\" src=\"https://dontstarve.wiki.gg/images/thumb/Hamlet_icon.png/32px-Hamlet_icon.png?e04a83\" width=\"32\" height=\"35\"></a><br>\n</p>\n\n<p class=\"mw-empty-elt\"></p>\n\n<p>The <b>Mant Suit</b> is a craftable <a href=\"https://dontstarve.wiki.gg/wiki/Armor\" class=\"mw-redirect\" title=\"Armor\">Armor</a> <a href=\"https://dontstarve.wiki.gg/wiki/Item\" class=\"mw-redirect\" title=\"Item\">Item</a> exclusive to the <i><a href=\"https://dontstarve.wiki.gg/wiki/Don%27t_Starve:_Hamlet\" title=\"Don&#x27;t Starve: Hamlet\">Don&#x27;t Starve: Hamlet</a></i> DLC. It is found in the <a href=\"https://dontstarve.wiki.gg/wiki/Fight_Tab\" title=\"Fight Tab\">Fight Tab</a>. It requires 5 <a href=\"https://dontstarve.wiki.gg/wiki/Chitin\" title=\"Chitin\">Chitin</a> and 1 <a href=\"https://dontstarve.wiki.gg/wiki/Log_Suit\" title=\"Log Suit\">Log Suit</a> to craft, and a <a href=\"https://dontstarve.wiki.gg/wiki/Science_Machine\" title=\"Science Machine\">Science Machine</a> to prototype.\n</p><p>It has a <a href=\"https://dontstarve.wiki.gg/wiki/Durability\" title=\"Durability\">Durability</a> of 450 and absorbs 80% of all physical damage. While being worn, the Mant Suit&#x27;s durability will slowly decrease even when not taking damage, lasting a maximum of 10 Days if no damage is taken. A <a href=\"https://dontstarve.wiki.gg/wiki/Sewing_Kit\" title=\"Sewing Kit\">Sewing Kit</a> will repair the Mant Suit by 50% (225 HP).\n</p><p>When worn along with a <a href=\"https://dontstarve.wiki.gg/wiki/Mant_Mask\" title=\"Mant Mask\">Mant Mask</a>, it also allows the player to disguise among the <a href=\"https://dontstarve.wiki.gg/wiki/Mant\" title=\"Mant\">Mants</a> and make them neutral. They will still defend themselves if attacked, but this way they can be approached safely. However, <a href=\"https://dontstarve.wiki.gg/wiki/Warrior_Mant\" class=\"mw-redirect\" title=\"Warrior Mant\">Warrior Mants</a> will not be fooled by the disguise.\n</p>\n<div class=\"tabber tabber--init\"><a class=\"tabber__tab\" id=\"Tools_and_Weapons-0-label\" href=\"https://dontstarve.wiki.gg/wiki/Mant_Suit#Tools_and_Weapons-0\">Tools and Weapons</a><a class=\"tabber__tab\" id=\"Craftable_Items-0-label\" href=\"https://dontstarve.wiki.gg/wiki/Mant_Suit#Craftable_Items-0\">Craftable Items</a><section class=\"tabber__section\"><p class=\"mw-empty-elt\"></p>\n<p class=\"mw-empty-elt\"></p><p class=\"mw-empty-elt\"></p><div></div>\n<div class=\"tabber tabber--init\"><a class=\"tabber__tab\" id=\"DST-0-label\" href=\"https://dontstarve.wiki.gg/wiki/Mant_Suit#DST-0\">DST</a><a class=\"tabber__tab\" id=\"DS-0-label\" href=\"https://dontstarve.wiki.gg/wiki/Mant_Suit#DS-0\">DS</a><a class=\"tabber__tab\" id=\"RoG-0-label\" href=\"https://dontstarve.wiki.gg/wiki/Mant_Suit#RoG-0\">RoG</a><a class=\"tabber__tab\" id=\"SW-0-label\" href=\"https://dontstarve.wiki.gg/wiki/Mant_Suit#SW-0\">SW</a><a class=\"tabber__tab\" id=\"Ham-0-label\" href=\"https://dontstarve.wiki.gg/wiki/Mant_Suit#Ham-0\">Ham</a><section class=\"tabber__section\"><p class=\"mw-empty-elt\"></p><p class=\"mw-empty-elt\"></p><p class=\"mw-empty-elt\"></p>\n <p class=\"mw-empty-elt\"></p><p class=\"mw-empty-elt\"></p>\n<p class=\"mw-empty-elt\"></p><p class=\"mw-empty-elt\"></p>\n<p class=\"mw-empty-elt\"></p><p class=\"mw-empty-elt\"></p>\n<p class=\"mw-empty-elt\"></p></section></div>\n<p class=\"mw-empty-elt\"></p></section></div>\n\n\n\n\n</div>",
  "images": [
    {
      "height": 64,
      "mime": "image/png",
      "src": "/assets/wiki/ae49252df3ba7e209e33a26795716950b903dec9e0530c155763bfe40255d1c3.png",
      "title": "File:Mant Suit.png",
      "width": 64
    }
  ],
  "pageId": 50764,
  "plainText": "Exclusive to:\nMant Suit\n\"Walk a mile in a Mant's carapace.\"\n×5 ×1\nTab\nTier\n80%\n450 hp / 10 Days\nDoes not stack\n\"antsuit\"\n“It's brittle.”\n–Wilson\n“This is the worst.”\n–Willow\n“Wolfgang just want to fit in.”\n–Wolfgang\n“As hollow as my heart.”\n–Wendy\n“INEFFICIENT PROTECTIVE CASING”\n–WX-78\n“A hollowed out arthropod.”\n–Wickerbottom\n“This feels a tad psychotic.”\n–Woodie\n“The indignities I've suffered...”\n–Maxwell\n“What a wonderful way to infiltrate a suspicious society.”\n–Wagstaff\n“This armör is nöt wörthy öf a shieldmaiden!”\n–Wigfrid\n“We could always use a spare thorax.”\n–Webber\n“Nice threads!”\n–Walani\n“There's no meat inside.”\n–Warly\n“'Tis an unpleasant bus'niss.”\n–Woodlegs\n“WILBA AM MERELY PLAYER”\n–Wilba\n“Makes Ch'rik Friends”\n–Wormwood\n“All dressed up and ready to cr'kit.”\n–Wheeler\nThe Mant Suit is a craftable Armor Item exclusive to the Don't Starve: Hamlet DLC. It is found in the Fight Tab. It requires 5 Chitin and 1 Log Suit to craft, and a Science Machine to prototype.\nIt has a Durability of 450 and absorbs 80% of all physical damage. While being worn, the Mant Suit's durability will slowly decrease even when not taking damage, lasting a maximum of 10 Days if no damage is taken. A Sewing Kit will repair the Mant Suit by 50% (225 HP).\nWhen worn along with a Mant Mask, it also allows the player to disguise among the Mants and make them neutral. They will still defend themselves if attacked, but this way they can be approached safely. However, Warrior Mants will not be fooled by the disguise.\nTools and WeaponsCraftable Items\nView or edit this template\nDon't Starve Tools and Weapons\nEquipped Tools\nUnequipped Tools\nLight\nBooks\nCircuits\nBattle Calls\nWatches\nWeapons\nSlingshot Parts\nThrowables\nStaffs\nAmulets\nBackpacks\nClothing\nStage Costumes\nArmor\nDSTDSRoGSWHam\nView or edit this template\nDon't Starve Together Craftable Items\nRegular Filters\nSurvivor Items\nWilson\nWillow\nWolfgang\nWendy\nWX-78\nWickerbottom\nWoodie\nWes\nMaxwell\nWigfrid\nWebber\nWarly\nWortox\nWormwood\nWinona\nWurt\nWalter\nWanda\nTools\nLight Sources\nPrototypers & Stations\nRefined Materials\nWeapons\nArmor\nClothing\nHealing\nMagic\nDecorations\nStructures\nStorage Solutions\nCooking\nFood & Gardening\nFishing\nSeafaring\nBeefalo Riding\nWinter Items\nSummer Items\nRain Gear\nCrafting Station Filters\nSpecial Event\nAncient Pseudoscience\nCarpentry\nCartography\nCritters\nCelestial\nBrightsmithy\nShadowcraft\nFabrication\nBottle Exchange\nCombrining Filter\nTea Brewing Filter\nSculptures\nSeasonings\nTrading\nTrading Hutch\nOfferings\nCawnival Creation\nTrinket Trove\nMad Science\nWinter's Feast Cooking\nSanctum Smithy Filter\nCustom Course Shack Filter\nView or edit this template\nDon't Starve Craftable Items\nTools\nLight\nSurvival\nFood\nScience\nFight\nStructures\nRefine\nMagic\nDress\nAncient\nBooks\nTinkering\nView or edit this template\nDon't Starve: Reign of Giants Craftable Items\nTools\nLight\nSurvival\nFood\nScience\nFight\nStructures\nRefine\nMagic\nDress\nAncient\nBooks\nTinkering\nView or edit this template\nDon't Starve Shipwrecked and Volcano Craftable Items\nTools\nLight\nNautical\nSurvival\nFood\nScience\nFight\nStructures\nRefine\nMagic\nDress\nVolcanic\nBooks\nTinkering\nView or edit this template\nDon't Starve Hamlet Craftable Items\nTools\nLight\nTreasure Hunting\nSurvival\nNautical\nFood\nScience\nFight\nStructures\nRefine\nMagic\nDress\nGreen Thumb\nBooks\nTinkering\nCity Planning\nRenovate\nFloors\nShelves\nPlantholders\nColumns\nWall Papers\nHanging Lamps\nOrnaments\nChairs\nHome Kits\nDoors\nWindows\nRugs\nLamps\nTables",
  "recipes": [],
  "redirectTarget": null,
  "revision": {
    "id": 510922,
    "sha1": "444559a7324797d2a9759c0892c155722bb692c0",
    "timestamp": "2023-11-04T11:35:01Z"
  },
  "schema_version": 1,
  "title": "Mant Suit",
  "wikitext": "{{Exclusivity|Hamlet}}\n{{Item Infobox\n|durability = 450 hp / 10 Days\n|perk = \n|stack = Does not stack\n|spawnCode = \"antsuit\"\n|ingredient1 = Chitin\n|multiplier1 = 5\n|ingredient2 = Log Suit\n|multiplier2 = 1\n|tab = Fight\n|tier = 1\n|description = Walk a mile in a Mant's carapace.\n|protection=80%}}\n{{Quotes\n|wilson = It's brittle.\n|willow = This is the worst.\n|wolfgang = Wolfgang just want to fit in.\n|wendy = As hollow as my heart.\n|wx78 = INEFFICIENT PROTECTIVE CASING\n|wickerbottom = A hollowed out arthropod.\n|woodie = This feels a tad psychotic.\n|maxwell = The indignities I've suffered...\n|wagstaff = What a wonderful way to infiltrate a suspicious society.\n|wigfrid = This armör is nöt wörthy öf a shieldmaiden!\n|webber = We could always use a spare thorax.\n|walani = Nice threads!\n|warly = There's no meat inside.\n|woodlegs = 'Tis an unpleasant bus'niss.\n|wilba = WILBA AM MERELY PLAYER\n|wormwood = Makes Ch'rik Friends\n|wheeler = All dressed up and ready to cr'kit.\n|choose = maxwell\n}}\nThe '''Mant Suit''' is a craftable [[Armor]] [[Item]] exclusive to the ''[[Don't Starve: Hamlet]]'' DLC. It is found in the [[Fight Tab]]. It requires 5 [[Chitin]] and 1 [[Log Suit]] to craft, and a [[Science Machine]] to prototype.\n\nIt has a [[Durability]] of 450 and absorbs 80% of all physical damage. While being worn, the Mant Suit's durability will slowly decrease even when not taking damage, lasting a maximum of 10 Days if no damage is taken. A [[Sewing Kit]] will repair the Mant Suit by 50% (225 HP).\n\nWhen worn along with a [[Mant Mask]], it also allows the player to disguise among the [[Mant]]s and make them neutral. They will still defend themselves if attacked, but this way they can be approached safely. However, [[Warrior Mant]]s will not be fooled by the disguise.\n<!--\n== {{Pic|32|Blueprint}} Gallery ==\n<gallery type=\"slideshow\" position=\"left\" hideaddbutton=\"true\" widths=\"350\">\nMant Suit Wilson.png|[[Wilson]] wearing a Mant Suit.\nMant Suit Willow.png|[[Willow]] wearing a Mant Suit.\nMant Suit Wolfgang.png|[[Wolfgang]] wearing a Mant Suit.\nMant Suit Wendy.png|[[Wendy]] wearing a Mant Suit.\nMant Suit WX-78.png|[[WX-78]] wearing a Mant Suit.\nMant Suit Wickerbottom.png|[[Wickerbottom]] wearing a Mant Suit.\nMant Suit Woodie.png|[[Woodie]] wearing a Mant Suit.\nMant Suit Wes.png|[[Wes]] wearing a Mant Suit.\nMant Suit Maxwell.png|[[Maxwell (character)|Maxwell]] wearing a Mant Suit.\nMant Suit Wagstaff.png|[[Wagstaff]] wearing a Mant Suit.\nMant Suit Wigfrid.png|[[Wigfrid]] wearing a Mant Suit.\nMant Suit Webber.png|[[Webber]] wearing a Mant Suit.\nMant Suit Walani.png|[[Walani]] wearing a Mant Suit.\nMant Suit Warly.png|[[Warly]] wearing a Mant Suit.\nMant Suit Wilbur.png|[[Wilbur]] wearing a Mant Suit.\nMant Suit Woodlegs.png|[[Woodlegs]] wearing a Mant Suit.\nMant Suit Wilba.png|[[Wilba]] wearing a Mant Suit.\nMant Suit Wormwood.png|[[Wormwood]] wearing a Mant Suit.\nMant Suit Wheeler.png|[[Wheeler]] wearing a Mant Suit.\n</gallery>\n--><tabber>\nTools and Weapons=\n{{Tools and Weapons}}\n|-|\nCraftable Items=\n{{Craftable Items|tool}}\n</tabber>\n[[vi:Mant Suit]]\n[[Category:Items]]\n[[Category:Equipable Items]]\n[[Category:Armor]]\n[[Category:Craftable Items]]\n[[Category:Fight Tab]]\n[[Category:Hamlet]]"
}
